yajbe/__init__.py
yajbe/decoder.py
yajbe/encoder.py
yajbe/freq.py
yajbe-0.0.7.dist-info/METADATA
yajbe-0.0.7.dist-info/WHEEL
yajbe-0.0.7.dist-info/RECORD
