Metadata-Version: 2.1
Name: yajbe
Version: 0.0.7
Summary: YAJBE is a compact binary data format built to be a drop-in replacement for JSON (JavaScript Object Notation).
Project-URL: Homepage, https://github.com/matteobertozzi/yajbe-data-format
Project-URL: Bug Tracker, https://github.com/matteobertozzi/yajbe-data-format/issues
Author-email: Matteo Bertozzi <mbertozzi@apache.org>
Classifier: License :: OSI Approved :: Apache Software License
Classifier: Operating System :: OS Independent
Classifier: Programming Language :: Python :: 3
Requires-Python: >=3.10
